examples/sentence_level/__init__.py
examples/sentence_level/wmt_2018/__init__.py
examples/sentence_level/wmt_2018/common/__init__.py
examples/sentence_level/wmt_2018/common/util/__init__.py
examples/sentence_level/wmt_2018/common/util/draw.py
examples/sentence_level/wmt_2018/common/util/normalizer.py
examples/sentence_level/wmt_2018/common/util/postprocess.py
examples/sentence_level/wmt_2018/common/util/reader.py
examples/sentence_level/wmt_2018/de_en/__init__.py
examples/sentence_level/wmt_2018/de_en/monotransquest.py
examples/sentence_level/wmt_2018/de_en/monotransquest_config.py
examples/sentence_level/wmt_2018/de_en/siamesetransquest.py
examples/sentence_level/wmt_2018/de_en/siamesetransquest_config.py
examples/sentence_level/wmt_2018/en_cs/__init__.py
examples/sentence_level/wmt_2018/en_cs/monotransquest.py
examples/sentence_level/wmt_2018/en_cs/monotransquest_config.py
examples/sentence_level/wmt_2018/en_cs/siamesetransquest.py
examples/sentence_level/wmt_2018/en_cs/siamesetransquest_config.py
examples/sentence_level/wmt_2018/en_de/__init__.py
examples/sentence_level/wmt_2018/en_de/nmt/__init__.py
examples/sentence_level/wmt_2018/en_de/nmt/monotransquest.py
examples/sentence_level/wmt_2018/en_de/nmt/monotransquest_config.py
examples/sentence_level/wmt_2018/en_de/nmt/siamesetransquest.py
examples/sentence_level/wmt_2018/en_de/nmt/siamesetransquest_config.py
examples/sentence_level/wmt_2018/en_de/smt/__init__.py
examples/sentence_level/wmt_2018/en_de/smt/monotransquest.py
examples/sentence_level/wmt_2018/en_de/smt/monotransquest_config.py
examples/sentence_level/wmt_2018/en_de/smt/siamesetransquest.py
examples/sentence_level/wmt_2018/en_de/smt/siamesetransquest_config.py
examples/sentence_level/wmt_2018/en_lv/__init__.py
examples/sentence_level/wmt_2018/en_lv/nmt/__init__.py
examples/sentence_level/wmt_2018/en_lv/nmt/monotransquest.py
examples/sentence_level/wmt_2018/en_lv/nmt/monotransquest_config.py
transquest-1.1.1.dist-info/LICENSE
transquest-1.1.1.dist-info/METADATA
transquest-1.1.1.dist-info/WHEEL
transquest-1.1.1.dist-info/top_level.txt
transquest-1.1.1.dist-info/RECORD
