Metadata-Version: 2.1
Name: transquest
Version: 1.1.1
Summary: Transformer based translation quality estimation
Home-page: https://github.com/TharinduDR/TransQuest
Author: Tharindu Ranasinghe
Author-email: rhtdranasinghe@gmail.com
License: UNKNOWN
Platform: UNKNOWN
Classifier: Intended Audience :: Science/Research
Classifier: License :: OSI Approved :: Apache Software License
Classifier: Programming Language :: Python :: 3
Classifier: Topic :: Scientific/Engineering :: Artificial Intelligence
Requires-Python: >=3.6
Requires-Dist: numpy
Requires-Dist: requests
Requires-Dist: tqdm (>=4.47.0)
Requires-Dist: regex
Requires-Dist: transformers (>=4.2.0)
Requires-Dist: scipy
Requires-Dist: scikit-learn
Requires-Dist: tensorboardx
Requires-Dist: pandas
Requires-Dist: tokenizers
Requires-Dist: matplotlib
Requires-Dist: wandb
Requires-Dist: sentencepiece
Requires-Dist: onnxruntime
Requires-Dist: seqeval
